tkparam/__init__.py
tkparam/tk_param.py
tkparam/tk_param_window.py
tkparam-0.1.1.dist-info/LICENSE
tkparam-0.1.1.dist-info/METADATA
tkparam-0.1.1.dist-info/WHEEL
tkparam-0.1.1.dist-info/top_level.txt
tkparam-0.1.1.dist-info/RECORD
