Metadata-Version: 2.1
Name: tkparam
Version: 0.1.1
Summary: tkparam provides a simple way to dynamically adjust parameters in a tkinter GUI panel, which is useful in looping programs
Author-email: bitCirno <1637131272@qq.com>
License: LICENSE
Project-URL: Repository, https://github.com/Rostave/tkparam
Project-URL: Issues, https://github.com/Rostave/tkparam/issues
Keywords: tkinter,dynamic parameter
Classifier: Programming Language :: Python :: 3
Classifier: License :: OSI Approved :: MIT License
Classifier: Operating System :: OS Independent
License-File: LICENSE
Requires-Dist: ttkbootstrap>=1.10.1
